{"current_mpg_team":"mpg_team_pVArFY4W1nn$$mpg_user_164215","teamsid":[{"id":"mpg_team_pVArFY4W1nn$$mpg_user_162149","name":"Les Girondingues de Bordeaux"},{"id":"mpg_team_pVArFY4W1nn$$mpg_user_164232","name":"Zlat FC"},{"id":"mpg_team_pVArFY4W1nn$$mpg_user_164215","name":"Dream Team"},{"id":"mpg_team_pVArFY4W1nn$$mpg_user_89215","name":"AS Ça t'étonne"},{"id":"mpg_team_pVArFY4W1nn$$mpg_user_164212","name":"Poppy Fire FC"},{"id":"mpg_team_pVArFY4W1nn$$mpg_user_215766","name":"Lass Team"},{"id":"mpg_team_pVArFY4W1nn$$mpg_user_251514","name":"asm"},{"id":"mpg_team_pVArFY4W1nn$$mpg_user_251575","name":" kazouf"}],"teams":{"mpg_team_pVArFY4W1nn$$mpg_user_162149":{"id":"mpg_team_pVArFY4W1nn$$mpg_user_162149","name":"Les Girondingues de Bordeaux","players":[{"id":"player_86873","club":"Lorient","firstname":"Benjamin","lastname":"Lecomte","position":1,"price_paid":9},{"id":"player_38314","club":"Saint Etienne","firstname":"Stéphane","lastname":"Ruffier","position":1,"price_paid":41},{"id":"player_13356","club":"Marseille","firstname":"Rod","lastname":"Fanni","position":2,"price_paid":12},{"id":"player_82313","club":"Bordeaux","firstname":"Nicolas","lastname":"Pallois","position":2,"price_paid":13},{"id":"player_39804","club":"Lille","firstname":"Julian","lastname":"Palmieri","position":2,"price_paid":12},{"id":"player_19670","club":"Saint Etienne","firstname":"Loic","lastname":"Perrin","position":2,"price_paid":14},{"id":"player_13939","club":"Dijon","firstname":"Cedric","lastname":"Varrault","position":2,"price_paid":13},{"id":"player_66959","club":"Nice","firstname":"Younès","lastname":"Belhanda","position":3,"price_paid":42},{"id":"player_169007","club":"Lyon","firstname":"Sergi","lastname":"Darder","position":3,"price_paid":14},{"id":"player_166552","club":"Lyon","firstname":"Nabil","lastname":"Fekir","position":3,"price_paid":35},{"id":"player_45082","club":"Caen","firstname":"Julien","lastname":"Féret","position":3,"price_paid":17},{"id":"player_19624","club":"Monaco","firstname":null,"lastname":"João Moutinho","position":3,"price_paid":41},{"id":"player_218005","club":"Bordeaux","firstname":"Adam","lastname":"Ounas","position":3,"price_paid":12},{"id":"player_115961","club":"Nantes","firstname":"Adrien","lastname":"Thomasson","position":3,"price_paid":6},{"id":"player_40721","club":"Toulouse","firstname":"Óscar","lastname":"Trejo","position":3,"price_paid":14},{"id":"player_37852","club":"Lyon","firstname":"Mathieu","lastname":"Valbuena","position":3,"price_paid":12},{"id":"player_40720","club":"Paris","firstname":"Edinson","lastname":"Cavani","position":4,"price_paid":101},{"id":"player_95715","club":"Paris","firstname":null,"lastname":"Lucas Moura","position":4,"price_paid":39},{"id":"player_220160","club":"Monaco","firstname":"Kylian","lastname":"Mbappe-Lottin","position":4,"price_paid":16},{"id":"player_167443","club":"Bordeaux","firstname":"Gaetan","lastname":"Laborde","position":4,"price_paid":10},{"id":"player_149535","club":"Angers","firstname":"Famara","lastname":"Diedhiou","position":4,"price_paid":16}]},"mpg_team_pVArFY4W1nn$$mpg_user_164232":{"id":"mpg_team_pVArFY4W1nn$$mpg_user_164232","name":"Zlat FC","players":[{"id":"player_61741","club":"Guingamp","firstname":"Karl-Johan","lastname":"Johnsson","position":1,"price_paid":10},{"id":"player_26894","club":"Nice","firstname":null,"lastname":"Dante","position":2,"price_paid":40},{"id":"player_208135","club":"Lyon","firstname":"Mouctar","lastname":"Diakhaby","position":2,"price_paid":7},{"id":"player_28136","club":"Montpellier","firstname":null,"lastname":"Hilton","position":2,"price_paid":25},{"id":"player_162654","club":"Monaco","firstname":null,"lastname":"Jemerson","position":2,"price_paid":25},{"id":"player_114546","club":"Toulouse","firstname":"Christopher","lastname":"Jullien","position":2,"price_paid":10},{"id":"player_201562","club":"Guingamp","firstname":"Marcus","lastname":"Coco","position":3,"price_paid":5},{"id":"player_46497","club":"Paris","firstname":"Ángel","lastname":"Di María","position":3,"price_paid":31},{"id":"player_168109","club":"Angers","firstname":"Cheikh","lastname":"Ndoye","position":3,"price_paid":30},{"id":"player_40808","club":"Bastia","firstname":"Prince","lastname":"Oniangué","position":3,"price_paid":12},{"id":"player_50996","club":"Caen","firstname":"Ronny","lastname":"Rodelin","position":3,"price_paid":28},{"id":"player_170137","club":"Bastia","firstname":"Allan","lastname":"Saint-Maximin","position":3,"price_paid":20},{"id":"player_39379","club":"Nancy","firstname":"Issiar","lastname":"Dia","position":4,"price_paid":20},{"id":"player_33103","club":"Metz","firstname":"Cheick","lastname":"Diabaté","position":4,"price_paid":12},{"id":"player_52635","club":"Lille","firstname":null,"lastname":"Eder","position":4,"price_paid":20},{"id":"player_73678","club":"Lorient","firstname":"Benjamin","lastname":"Moukandjo","position":4,"price_paid":20},{"id":"player_60319","club":"Caen","firstname":"Ivan","lastname":"Santini","position":4,"price_paid":20},{"id":"player_193454","club":"Angers","firstname":"Karl","lastname":"Toko Ekambi","position":4,"price_paid":10},{"id":"player_37901","club":"Marseille","firstname":"Dimitri","lastname":"Payet","position":3,"price_paid":109},{"id":"player_212887","club":"Guingamp","firstname":"Theo","lastname":"Guivarch","position":1,"price_paid":1}]},"mpg_team_pVArFY4W1nn$$mpg_user_164215":{"id":"mpg_team_pVArFY4W1nn$$mpg_user_164215","name":"Dream Team","players":[{"id":"player_115851","club":"Nice","firstname":"Yoan","lastname":"Cardinale","position":1,"price_paid":24},{"id":"player_93619","club":"Dijon","firstname":"Baptiste","lastname":"Reynet","position":1,"price_paid":17},{"id":"player_212752","club":"Nice","firstname":null,"lastname":"Dalbert","position":2,"price_paid":13},{"id":"player_129479","club":"Paris","firstname":"Presnel","lastname":"Kimpembe","position":2,"price_paid":12},{"id":"player_61739","club":"Nice","firstname":"Maxime","lastname":"Le Marchand","position":2,"price_paid":5},{"id":"player_173211","club":"Lyon","firstname":"Emanuel","lastname":"Mammana","position":2,"price_paid":9},{"id":"player_9809","club":"Paris","firstname":null,"lastname":"Maxwell","position":2,"price_paid":15},{"id":"player_93605","club":"Paris","firstname":"Thomas","lastname":"Meunier","position":2,"price_paid":17},{"id":"player_42714","club":"Guingamp","firstname":"Jérémy","lastname":"Sorbon","position":2,"price_paid":13},{"id":"player_78275","club":"Nice","firstname":"Arnaud","lastname":"Souquet","position":2,"price_paid":5},{"id":"player_98746","club":"Dijon","firstname":"Mehdi","lastname":"Abeid","position":3,"price_paid":10},{"id":"player_55948","club":"Rennes","firstname":"Benjamin","lastname":"André","position":3,"price_paid":15},{"id":"player_172987","club":"Monaco","firstname":null,"lastname":"Boschilia","position":3,"price_paid":13},{"id":"player_55264","club":"Montpellier","firstname":"Ryad","lastname":"Boudebouz","position":3,"price_paid":16},{"id":"player_59963","club":"Lyon","firstname":"Maxime","lastname":"Gonalons","position":3,"price_paid":31},{"id":"player_212325","club":"Dijon","firstname":"Pierre","lastname":"Lees-Melou","position":3,"price_paid":10},{"id":"player_167449","club":"Monaco","firstname":"Thomas","lastname":"Lemar","position":3,"price_paid":29},{"id":"player_54782","club":"Paris","firstname":"Javier","lastname":"Pastore","position":3,"price_paid":21},{"id":"player_120743","club":"Paris","firstname":"Adrien","lastname":"Rabiot","position":3,"price_paid":14},{"id":"player_195982","club":"Bordeaux","firstname":"Valentin","lastname":"Vada","position":3,"price_paid":9},{"id":"player_40815","club":"Marseille","firstname":"William","lastname":"Vainqueur","position":3,"price_paid":14},{"id":"player_98914","club":"Monaco","firstname":"Guido","lastname":"Carrillo","position":4,"price_paid":17},{"id":"player_147577","club":"Dijon","firstname":"Lois","lastname":"Diony","position":4,"price_paid":12},{"id":"player_37998","club":"Marseille","firstname":"Bafétimbi","lastname":"Gomis","position":4,"price_paid":56},{"id":"player_126177","club":"Toulouse","firstname":"Corentin","lastname":"Jean","position":4,"price_paid":15},{"id":"player_103124","club":"Nantes","firstname":"Emiliano","lastname":"Sala","position":4,"price_paid":15}]},"mpg_team_pVArFY4W1nn$$mpg_user_89215":{"id":"mpg_team_pVArFY4W1nn$$mpg_user_89215","name":"AS Ça t'étonne","players":[{"id":"player_6244","club":"Bordeaux","firstname":"Cédric","lastname":"Carrasso","position":1,"price_paid":23},{"id":"player_44136","club":"Bastia","firstname":"Jean-Louis","lastname":"Leca","position":1,"price_paid":10},{"id":"player_12656","club":"Lille","firstname":"Franck","lastname":"Beria","position":2,"price_paid":6},{"id":"player_38002","club":"Montpellier","firstname":"Daniel","lastname":"Congré","position":2,"price_paid":13},{"id":"player_129478","club":"Guingamp","firstname":"Jordan","lastname":"Ikoko","position":2,"price_paid":9},{"id":"player_80357","club":"Rennes","firstname":null,"lastname":"Mexer","position":2,"price_paid":12},{"id":"player_93289","club":"Montpellier","firstname":"Jérôme","lastname":"Roussillon","position":2,"price_paid":13},{"id":"player_102747","club":"Monaco","firstname":"Djibril","lastname":"Sidibe","position":2,"price_paid":32},{"id":"player_44488","club":"Lyon","firstname":"Mapou","lastname":"Yanga-Mbiwa","position":2,"price_paid":25},{"id":"player_39905","club":"Guingamp","firstname":"Moustapha","lastname":"Diallo","position":3,"price_paid":17},{"id":"player_213965","club":"Marseille","firstname":"Maxime","lastname":"Lopez","position":3,"price_paid":18},{"id":"player_11527","club":"Paris","firstname":"Thiago","lastname":"Motta","position":3,"price_paid":31},{"id":"player_109653","club":"Lille","firstname":null,"lastname":"Rony Lopes","position":3,"price_paid":13},{"id":"player_48768","club":"Bordeaux","firstname":"Younousse","lastname":"Sankhare","position":3,"price_paid":10},{"id":"player_34392","club":"Montpellier","firstname":"Stéphane","lastname":"Sessegnon","position":3,"price_paid":11},{"id":"player_106824","club":"Lyon","firstname":"Memphis","lastname":"Depay","position":4,"price_paid":103},{"id":"player_213401","club":"Rennes","firstname":"Aldo","lastname":"Kalulu","position":4,"price_paid":4},{"id":"player_59966","club":"Lyon","firstname":"Alexandre","lastname":"Lacazette","position":4,"price_paid":110},{"id":"player_169141","club":"Montpellier","firstname":"Steve","lastname":"Mounie","position":4,"price_paid":19},{"id":"player_108168","club":"Nice","firstname":"Alassane","lastname":"Pléa","position":4,"price_paid":29},{"id":"player_154011","club":"Angers","firstname":"Flavien","lastname":"Tait","position":3,"price_paid":3}]},"mpg_team_pVArFY4W1nn$$mpg_user_164212":{"id":"mpg_team_pVArFY4W1nn$$mpg_user_164212","name":"Poppy Fire FC","players":[{"id":"player_84182","club":"Paris","firstname":"Alphonse","lastname":"Areola","position":1,"price_paid":12},{"id":"player_37769","club":"Marseille","firstname":"Yohann","lastname":"Pelé","position":1,"price_paid":25},{"id":"player_80226","club":"Paris","firstname":"Serge","lastname":"Aurier","position":2,"price_paid":38},{"id":"player_37758","club":"Nice","firstname":"Paul","lastname":"Baysse","position":2,"price_paid":15},{"id":"player_60121","club":"Lille","firstname":"Sébastien","lastname":"Corchia","position":2,"price_paid":21},{"id":"player_79237","club":"Saint Etienne","firstname":"Florentin","lastname":"Pogba","position":2,"price_paid":16},{"id":"player_54772","club":"Lyon","firstname":null,"lastname":"Rafael","position":2,"price_paid":14},{"id":"player_66957","club":"Marseille","firstname":"Rémy","lastname":"Cabella","position":3,"price_paid":21},{"id":"player_92985","club":"Paris","firstname":"Julian","lastname":"Draxler","position":3,"price_paid":48},{"id":"player_115858","club":"Lyon","firstname":"Rachid","lastname":"Ghezzal","position":3,"price_paid":28},{"id":"player_27669","club":"Rennes","firstname":"Yoann","lastname":"Gourcuff","position":3,"price_paid":25},{"id":"player_67276","club":"Saint Etienne","firstname":"Romain","lastname":"Hamouma","position":3,"price_paid":25},{"id":"player_20468","club":"Marseille","firstname":null,"lastname":"Lass Diarra","position":3,"price_paid":30},{"id":"player_122775","club":"Marseille","firstname":"Morgan","lastname":"Sanson","position":3,"price_paid":22},{"id":"player_95434","club":"Marseille","firstname":"Florian","lastname":"Thauvin","position":3,"price_paid":20},{"id":"player_42493","club":"Nice","firstname":"Mario","lastname":"Balotelli","position":4,"price_paid":35},{"id":"player_193409","club":"Nantes","firstname":"Yacine","lastname":"Bammou","position":4,"price_paid":12}]},"mpg_team_pVArFY4W1nn$$mpg_user_215766":{"id":"mpg_team_pVArFY4W1nn$$mpg_user_215766","name":"Lass Team","players":[{"id":"player_42713","club":"Rennes","firstname":"Benoit","lastname":"Costil","position":1,"price_paid":48},{"id":"player_204739","club":"Toulouse","firstname":"Alban","lastname":"Lafont","position":1,"price_paid":15},{"id":"player_44287","club":"Caen","firstname":"Damien","lastname":"Da Silva","position":2,"price_paid":7},{"id":"player_219924","club":"Toulouse","firstname":"Issa","lastname":"Diop","position":2,"price_paid":15},{"id":"player_183779","club":"Nantes","firstname":"Léo","lastname":"Dubois","position":2,"price_paid":8},{"id":"player_218705","club":"Rennes","firstname":"Joris","lastname":"Gnagnon","position":2,"price_paid":4},{"id":"player_102739","club":"Guingamp","firstname":"Christophe","lastname":"Kerbrat","position":2,"price_paid":12},{"id":"player_83577","club":"Saint Etienne","firstname":"Leo","lastname":"Lacroix","position":2,"price_paid":17},{"id":"player_83340","club":"Saint Etienne","firstname":"Kevin","lastname":"Malcuit","position":2,"price_paid":25},{"id":"player_111291","club":"Guingamp","firstname":"Fernando","lastname":"Marçal","position":2,"price_paid":10},{"id":"player_213940","club":"Guingamp","firstname":"Ludovic","lastname":"Blas","position":3,"price_paid":5},{"id":"player_151912","club":"Lorient","firstname":"Jimmy","lastname":"Cabot","position":3,"price_paid":8},{"id":"player_151873","club":"Nice","firstname":"Wylan","lastname":"Cyprien","position":3,"price_paid":32},{"id":"player_54533","club":"Guingamp","firstname":"Nill","lastname":"de Pauw","position":3,"price_paid":17},{"id":"player_45084","club":"Guingamp","firstname":"Lucas","lastname":"Deaux","position":3,"price_paid":10},{"id":"player_61704","club":"Toulouse","firstname":"Jimmy","lastname":"Durmaz","position":3,"price_paid":8},{"id":"player_181092","club":"Bordeaux","firstname":null,"lastname":"Malcom","position":3,"price_paid":26},{"id":"player_55343","club":"Guingamp","firstname":"Yannis","lastname":"Salibur","position":3,"price_paid":18},{"id":"player_168568","club":"Lyon","firstname":"Corentin","lastname":"Tolisso","position":3,"price_paid":40},{"id":"player_61170","club":"Paris","firstname":"Marco","lastname":"Verratti","position":3,"price_paid":42},{"id":"player_68690","club":"Toulouse","firstname":"Martin","lastname":"Braithwaite","position":4,"price_paid":30},{"id":"player_27675","club":"Guingamp","firstname":"Jimmy","lastname":"Briand","position":4,"price_paid":26},{"id":"player_178492","club":"Bastia","firstname":"Enzo","lastname":"Crivelli","position":4,"price_paid":41},{"id":"player_55711","club":"Saint Etienne","firstname":"Robert","lastname":"Beric","position":4,"price_paid":13},{"id":"player_108143","club":"Nantes","firstname":"Mariusz","lastname":"Stepinski","position":4,"price_paid":12}]},"mpg_team_pVArFY4W1nn$$mpg_user_251514":{"id":"mpg_team_pVArFY4W1nn$$mpg_user_251514","name":"asm","players":[{"id":"player_7446","club":"Monaco","firstname":"Morgan","lastname":"De Sanctis","position":1,"price_paid":1},{"id":"player_60582","club":"Monaco","firstname":"Danijel","lastname":"Subasic","position":1,"price_paid":35},{"id":"player_37938","club":"Rennes","firstname":"Romain","lastname":"Danze","position":2,"price_paid":20},{"id":"player_71403","club":"Monaco","firstname":"Kamil","lastname":"Glik","position":2,"price_paid":15},{"id":"player_102826","club":"Monaco","firstname":"Benjamin","lastname":"Mendy","position":2,"price_paid":38},{"id":"player_15930","club":"Monaco","firstname":"Andrea","lastname":"Raggi","position":2,"price_paid":12},{"id":"player_39294","club":"Marseille","firstname":null,"lastname":"Rolando","position":2,"price_paid":40},{"id":"player_192292","club":"Monaco","firstname":"Almamy","lastname":"Touré","position":2,"price_paid":6},{"id":"player_165809","club":"Monaco","firstname":null,"lastname":"Bernardo Silva","position":3,"price_paid":50},{"id":"player_194141","club":"Nice","firstname":"Vincent","lastname":"Koziello","position":3,"price_paid":13},{"id":"player_9980","club":"Nancy","firstname":"Benoit","lastname":"Pedretti","position":3,"price_paid":17},{"id":"player_12057","club":"Bordeaux","firstname":"Jaroslav","lastname":"Plasil","position":3,"price_paid":13},{"id":"player_73879","club":"Lille","firstname":"Nicolas","lastname":"de Preville","position":4,"price_paid":18},{"id":"player_48847","club":"Monaco","firstname":null,"lastname":"Falcao","position":4,"price_paid":58},{"id":"player_97041","club":"Monaco","firstname":"Valère","lastname":"Germain","position":4,"price_paid":62},{"id":"player_148011","club":"Bordeaux","firstname":"Diego","lastname":"Rolan","position":4,"price_paid":62},{"id":"player_73494","club":"Paris","firstname":"Grzegorz","lastname":"Krychowiak","position":3,"price_paid":18}]},"mpg_team_pVArFY4W1nn$$mpg_user_251575":{"id":"mpg_team_pVArFY4W1nn$$mpg_user_251575","name":" kazouf","players":[{"id":"player_59957","club":"Lyon","firstname":null,"lastname":"Anthony Lopes","position":1,"price_paid":41},{"id":"player_119744","club":"Angers","firstname":"Mathieu","lastname":"Michel","position":1,"price_paid":11},{"id":"player_116643","club":"Monaco","firstname":null,"lastname":"Fabinho","position":2,"price_paid":50},{"id":"player_89068","club":"Paris","firstname":"Layvin","lastname":"Kurzawa","position":2,"price_paid":16},{"id":"player_116406","club":"Paris","firstname":null,"lastname":"Marquinhos","position":2,"price_paid":18},{"id":"player_145221","club":"Toulouse","firstname":"Issiaga","lastname":"Sylla","position":2,"price_paid":10},{"id":"player_51090","club":"Paris","firstname":null,"lastname":"Thiago Silva","position":2,"price_paid":41},{"id":"player_169102","club":"Monaco","firstname":"Tiemoué","lastname":"Bakayoko","position":3,"price_paid":14},{"id":"player_91070","club":"Nice","firstname":"Valentin","lastname":"Eysseric","position":3,"price_paid":18},{"id":"player_37971","club":"Paris","firstname":"Blaise","lastname":"Matuidi","position":3,"price_paid":29},{"id":"player_170271","club":"Nice","firstname":"Jean Michael","lastname":"Seri","position":3,"price_paid":25},{"id":"player_73965","club":"Toulouse","firstname":"Andy","lastname":"Delort","position":4,"price_paid":28},{"id":"player_181284","club":"Paris","firstname":null,"lastname":"Gonçalo Guedes","position":4,"price_paid":80},{"id":"player_184095","club":"Caen","firstname":"Yann","lastname":"Karamoh","position":4,"price_paid":9},{"id":"player_82184","club":"Lorient","firstname":null,"lastname":"Majeed Waris","position":4,"price_paid":19}]}}}